stack_graphs_python_bindings-0.0.14.dist-info/METADATA
stack_graphs_python_bindings-0.0.14.dist-info/WHEEL
stack_graphs_python_bindings-0.0.14.dist-info/licenses/LICENSE
stack_graphs_python/__init__.py
stack_graphs_python/__init__.pyi
stack_graphs_python/py.typed
stack_graphs_python/stack_graphs_python.cpython-312-darwin.so
stack_graphs_python_bindings-0.0.14.dist-info/RECORD
